collie/__init__.py
collie/ccnews_extractor.py
collie/constraint_renderer.py
collie/constraints.py
collie/english_extractor.py
collie/extract_constraints.py
collie/extractor_utils.py
collie/gutenberg_extractor.py
collie/models.py
collie/wiki_extractor.py
collie/examples/extract.py
collie/examples/para_constraints.py
collie/examples/passage_constraints.py
collie/examples/sent_constraints.py
collie/examples/sources.py
collie/examples/validate.py
collie/examples/word_constraints.py
scripts/run_api_models.py
scripts/run_gpu_models.py
tests/test_constraints.py
collie_bench-0.1.0.dist-info/LICENSE
collie_bench-0.1.0.dist-info/METADATA
collie_bench-0.1.0.dist-info/WHEEL
collie_bench-0.1.0.dist-info/top_level.txt
collie_bench-0.1.0.dist-info/RECORD
