Metadata-Version: 2.1
Name: collie-bench
Version: 0.1.0
Summary: Official Implementation of "COLLIE: Systematic Construction of Constrained Text Generation Tasks"
Author-email: Howard Chen <howardchen@cs.princeton.edu>
License: MIT License
Project-URL: Homepage, https://github.com/princeton-nlp/Collie
Keywords: large language model,llm,constrained generation,benchmark
Classifier: License :: OSI Approved :: MIT License
Classifier: Programming Language :: Python :: 3
Classifier: Programming Language :: Python :: 3.7
Classifier: Programming Language :: Python :: 3.8
Classifier: Programming Language :: Python :: 3.9
Classifier: Programming Language :: Python :: 3.10
Classifier: Programming Language :: Python :: 3.11
Classifier: Intended Audience :: Science/Research
Classifier: Topic :: Scientific/Engineering :: Artificial Intelligence
Requires-Python: >=3.7
License-File: LICENSE
Requires-Dist: openai
Requires-Dist: aiolimiter
Requires-Dist: rich
Requires-Dist: fschat
